{
  "db_name": "MySQL",
  "query": "SELECT * FROM t_client_config WHERE client_id = ?",
  "describe": {
    "columns": [
      {
        "ordinal": 0,
        "name": "id",
        "type_info": {
          "type": "LongLong",
          "flags": "NOT_NULL | PRIMARY_KEY | AUTO_INCREMENT",
          "char_set": 63,
          "max_size": 22
        }
      },
      {
        "ordinal": 1,
        "name": "client_id",
        "type_info": {
          "type": "VarString",
          "flags": "NOT_NULL | UNIQUE_KEY | NO_DEFAULT_VALUE",
          "char_set": 224,
          "max_size": 128
        }
      },
      {
        "ordinal": 2,
        "name": "name",
        "type_info": {
          "type": "VarString",
          "flags": "NOT_NULL | NO_DEFAULT_VALUE",
          "char_set": 224,
          "max_size": 512
        }
      },
      {
        "ordinal": 3,
        "name": "logo",
        "type_info": {
          "type": "Blob",
          "flags": "NOT_NULL | BLOB | NO_DEFAULT_VALUE",
          "char_set": 224,
          "max_size": 262140
        }
      },
      {
        "ordinal": 4,
        "name": "description",
        "type_info": {
          "type": "Blob",
          "flags": "NOT_NULL | BLOB | NO_DEFAULT_VALUE",
          "char_set": 224,
          "max_size": 262140
        }
      },
      {
        "ordinal": 5,
        "name": "redirect_url",
        "type_info": {
          "type": "Blob",
          "flags": "BLOB",
          "char_set": 224,
          "max_size": 262140
        }
      },
      {
        "ordinal": 6,
        "name": "updated_at",
        "type_info": {
          "type": "Timestamp",
          "flags": "NOT_NULL | BINARY | TIMESTAMP | ON_UPDATE_NOW",
          "char_set": 63,
          "max_size": 19
        }
      },
      {
        "ordinal": 7,
        "name": "created_at",
        "type_info": {
          "type": "Timestamp",
          "flags": "NOT_NULL | BINARY | TIMESTAMP",
          "char_set": 63,
          "max_size": 19
        }
      }
    ],
    "parameters": {
      "Right": 1
    },
    "nullable": [
      false,
      false,
      false,
      false,
      false,
      true,
      false,
      false
    ]
  },
  "hash": "04f0870f2a859342f90796af681ba695d043d9800f6d082d9dfac72b88000d4a"
}
